[{
    "template":{
        "radar_overview":{
            "hidden":true,
            "layers": [{
                "shape":"canvas_parent",
                "layers": [{
                    "shape":"radar_overview_panel_open",
                    "id":"radar_overview_page"
                }]
            }]
        }
    },
    "shapes": {
        "radar_overview_panel_open":{
            "passive":{
                "pos":{
                    "unit":"%",
                    "top":8,
                    "left":4
                },
                "shape":{
                    "unit":"px",
                    "width":280,
                    "height":280
                },
                "border": {
                    "unit":"px",
                    "color":  "color_slider_border_hover",
                    "line_width":1
                },
                "draw_callback":{
                    "source":"radar_overview",
                    "line_width": 3,
                    "top_value": 1,
                    "color": [1, 0.2, 0.5,1]
                }
            }
        }
    }
}]